mirnablast
