Metadata-Version: 2.1
Name: miRNABlast
Version: 0.0.2
Summary: Use mature query miRNA sequences to BLAST the genome, fold the flanking sequences of the subjects to find possible homologous miRNA locus
Home-page: https://github.com/SouthernCD/miRNABlast
Author: Yuxing Xu
Author-email: xuyuxing@mail.kib.ac.cn
License: MIT
Classifier: Development Status :: 5 - Production/Stable
Classifier: Environment :: Console
Classifier: Intended Audience :: Science/Research
Classifier: Natural Language :: English
Classifier: Operating System :: Unix
Classifier: Programming Language :: Python :: 3.7
Classifier: Programming Language :: Python :: 3.6
Classifier: Programming Language :: Python :: 3.5
Classifier: Programming Language :: Python :: Implementation :: PyPy
Classifier: Topic :: Scientific/Engineering :: Bio-Informatics
Requires-Python: >=3.5
License-File: LICENSE
